sentry2csv/__init__.py
sentry2csv/sentry2csv.py
sentry2csv-1.3.0.dist-info/LICENSE
sentry2csv-1.3.0.dist-info/METADATA
sentry2csv-1.3.0.dist-info/WHEEL
sentry2csv-1.3.0.dist-info/entry_points.txt
sentry2csv-1.3.0.dist-info/top_level.txt
sentry2csv-1.3.0.dist-info/RECORD
