Metadata-Version: 2.1
Name: sentry2csv
Version: 1.3.0
Summary: Export Sentry issues to CSV for further analysis
Home-page: https://github.com/sparkmeter/sentry2csv
Author: SparkMeter
Author-email: aru.sahni@sparkmeter.io
License: UNKNOWN
Project-URL: Bug Tracker, https://github.com/sparkmeter/sentry2csv/issues
Project-URL: Source Code, https://github.com/sparkmeter/sentry2csv
Platform: UNKNOWN
Classifier: Programming Language :: Python :: 3.7
Classifier: Programming Language :: Python :: 3.8
Classifier: Programming Language :: Python :: 3.9
Classifier: Programming Language :: Python :: 3.10
Classifier: Development Status :: 3 - Alpha
Classifier: Environment :: Console
Classifier: License :: OSI Approved :: MIT License
Requires-Python: >=3.7
Requires-Dist: aiohttp (==3.8.1)
Provides-Extra: dev
Requires-Dist: aioresponses (==0.7.3) ; extra == 'dev'
Requires-Dist: asynctest (==0.13.0) ; extra == 'dev'
Requires-Dist: black (==22.3.0) ; extra == 'dev'
Requires-Dist: mypy (==0.931) ; extra == 'dev'
Requires-Dist: mypy-extensions (==0.4.3) ; extra == 'dev'
Requires-Dist: types-setuptools (==57.4.9) ; extra == 'dev'
Requires-Dist: pylint (==2.12.2) ; extra == 'dev'
Requires-Dist: pytest (==7.0.1) ; extra == 'dev'
Requires-Dist: pytest-asyncio (==0.18.1) ; extra == 'dev'
Requires-Dist: pytest-cov (==2.8.1) ; extra == 'dev'
Requires-Dist: pytest-mock (==1.11.2) ; extra == 'dev'
Requires-Dist: typing-extensions (==4.2.0) ; extra == 'dev'
